{
  "document_set_id": "APDS-2026-0009",
  "part_no": "SFS-E10-APX",
  "entity": "Cedar Ridge Trust",
  "period": "2026-07",
  "currency": "USD",
  "documents": [
    {
      "doc_type": "invoice_posting_report",
      "document_id": "POST-2026-0009",
      "file_name": "invoice_posting_report_20260731_0009.json",
      "header_date": "2026-07-31",
      "ledger_code": "AP-3000",
      "posting_proof_cents": 0,
      "gl_recap": {
        "debit_cents": 1675836,
        "credit_cents": 1675836
      },
      "posting_totals": {
        "debit_cents": 1675836,
        "credit_cents": 1675836
      },
      "posted_counts": {
        "invoices": 3,
        "entries": 6,
        "job_cost_entries": 1
      },
      "rejected": {
        "invoices": 0,
        "entries": 0,
        "job_cost_entries": 0
      },
      "notices": [
        "job-cost entries not created for 2 ledger-only invoice(s)"
      ],
      "error_markers": [],
      "job_cost_recap_cents": 491500,
      "payable_cost_total_cents": 490000
    },
    {
      "doc_type": "payment_selection_register",
      "document_id": "PAYSEL-2026-0009",
      "payment_date": "2026-07-31",
      "payment_method": "electronic payment provider",
      "funding": {
        "confirmed": true,
        "confirmed_on": "2026-07-30",
        "bank": "Northgate Demo Bank",
        "amount_cents": 1675836
      },
      "payments": [
        {
          "payment_id": "PAY-2026-0901",
          "vendor_id": "VEN-1001",
          "vendor_name": "Ironwood Sandbox Supply Co",
          "document_number": "INV-2026-0901",
          "purchase_order": "PO-2026-0901",
          "ledger_code": "AP-3000",
          "gross_cents": 490000,
          "retention_rate_bps": 1000,
          "retention_cents": 49000,
          "tax_rate_bps": 875,
          "tax_cents": 38587,
          "amount_cents": 479587,
          "first_payment": true,
          "w9_on_file": true,
          "progress_billing": true,
          "lien_waiver": {
            "required": true,
            "vendor_received": true,
            "lower_tier_required": [
              "VEN-2001",
              "VEN-2002"
            ],
            "lower_tier_received": [
              "VEN-2001",
              "VEN-2002"
            ]
          },
          "insurance": {
            "certificate_on_file": true,
            "expires_on": "2026-12-31",
            "general_liability_cents": 200000000,
            "auto_liability_cents": 100000000,
            "umbrella_cents": 500000000
          },
          "contract_minimums": {
            "general_liability_cents": 100000000,
            "auto_liability_cents": 50000000,
            "umbrella_cents": 200000000
          },
          "off_cycle": false,
          "off_cycle_approval": null,
          "off_cycle_limit_cents": 2000000
        },
        {
          "payment_id": "PAY-2026-0902",
          "vendor_id": "VEN-1002",
          "vendor_name": "Foxglove Mock Freight LLC",
          "document_number": "INV-2026-0902",
          "purchase_order": "PO-2026-0902",
          "ledger_code": "AP-3000",
          "gross_cents": 697500,
          "retention_rate_bps": 0,
          "retention_cents": 0,
          "tax_rate_bps": 875,
          "tax_cents": 61031,
          "amount_cents": 758531,
          "first_payment": false,
          "w9_on_file": true,
          "progress_billing": false,
          "lien_waiver": {
            "required": false,
            "vendor_received": false,
            "lower_tier_required": [],
            "lower_tier_received": []
          },
          "insurance": {
            "certificate_on_file": true,
            "expires_on": "2026-12-31",
            "general_liability_cents": 200000000,
            "auto_liability_cents": 100000000,
            "umbrella_cents": 500000000
          },
          "contract_minimums": {
            "general_liability_cents": 100000000,
            "auto_liability_cents": 50000000,
            "umbrella_cents": 200000000
          },
          "off_cycle": false,
          "off_cycle_approval": null,
          "off_cycle_limit_cents": 2000000
        },
        {
          "payment_id": "PAY-2026-0903",
          "vendor_id": "VEN-1003",
          "vendor_name": "Harborview Demo Services Inc",
          "document_number": "INV-2026-0903",
          "purchase_order": "PO-2026-0903",
          "ledger_code": "AP-3000",
          "gross_cents": 402500,
          "retention_rate_bps": 0,
          "retention_cents": 0,
          "tax_rate_bps": 875,
          "tax_cents": 35218,
          "amount_cents": 437718,
          "first_payment": false,
          "w9_on_file": true,
          "progress_billing": false,
          "lien_waiver": {
            "required": false,
            "vendor_received": false,
            "lower_tier_required": [],
            "lower_tier_received": []
          },
          "insurance": {
            "certificate_on_file": true,
            "expires_on": "2026-12-31",
            "general_liability_cents": 200000000,
            "auto_liability_cents": 100000000,
            "umbrella_cents": 500000000
          },
          "contract_minimums": {
            "general_liability_cents": 100000000,
            "auto_liability_cents": 50000000,
            "umbrella_cents": 200000000
          },
          "off_cycle": true,
          "off_cycle_approval": {
            "approver": "approver-d",
            "approved_on": "2026-07-30"
          },
          "off_cycle_limit_cents": 2000000
        }
      ]
    },
    {
      "doc_type": "workflow_routing_matrix",
      "document_id": "ROUTE-2026-0009",
      "as_of": "2026-07-31",
      "jobs": [
        {
          "job_id": "JOB-2026-0001",
          "active": true,
          "workflows": [
            "WF-STD-01"
          ]
        },
        {
          "job_id": "JOB-2026-0002",
          "active": true,
          "workflows": [
            "WF-STD-02"
          ]
        },
        {
          "job_id": "JOB-2026-0003",
          "active": true,
          "workflows": [
            "WF-DIRECT-01"
          ]
        },
        {
          "job_id": "JOB-2025-0009",
          "active": false,
          "workflows": []
        }
      ],
      "workflows": [
        {
          "workflow_id": "WF-STD-01",
          "approvers": [
            "approver-a",
            "approver-b"
          ],
          "final_review_group": "review-group-one",
          "data_entry_role": "clerk-one",
          "final_review_role": "reviewer-one",
          "direct_post": false
        },
        {
          "workflow_id": "WF-STD-02",
          "approvers": [
            "approver-c"
          ],
          "final_review_group": "review-group-two",
          "data_entry_role": "clerk-two",
          "final_review_role": "reviewer-two",
          "direct_post": false
        },
        {
          "workflow_id": "WF-DIRECT-01",
          "approvers": [
            "approver-d"
          ],
          "final_review_group": "review-group-one",
          "data_entry_role": "clerk-three",
          "final_review_role": "reviewer-three",
          "direct_post": true
        }
      ],
      "preapproved_direct_post": [
        "WF-DIRECT-01"
      ]
    },
    {
      "doc_type": "information_reporting_register",
      "document_id": "IR-2026-0009",
      "tax_year": 2026,
      "threshold_cents": 60000,
      "vendors": [
        {
          "vendor_id": "VEN-1001",
          "vendor_name": "Ironwood Sandbox Supply Co",
          "entity": "Cedar Ridge Trust",
          "ytd_paid_cents": 1510000,
          "reportable": true,
          "evaluated": true,
          "tin": "00-1000091",
          "form_filed": true
        },
        {
          "vendor_id": "VEN-1002",
          "vendor_name": "Foxglove Mock Freight LLC",
          "entity": "Cedar Ridge Trust",
          "ytd_paid_cents": 2025000,
          "reportable": true,
          "evaluated": true,
          "tin": "00-1000092",
          "form_filed": true
        },
        {
          "vendor_id": "VEN-1003",
          "vendor_name": "Harborview Demo Services Inc",
          "entity": "Cedar Ridge Trust",
          "ytd_paid_cents": 2000000,
          "reportable": true,
          "evaluated": true,
          "tin": "00-1000093",
          "form_filed": true
        },
        {
          "vendor_id": "VEN-1004",
          "vendor_name": "Birchwood Mock Rentals LLC",
          "entity": "Cedar Ridge Trust",
          "ytd_paid_cents": 27500,
          "reportable": false,
          "evaluated": false,
          "tin": "00-1000094",
          "form_filed": false
        }
      ],
      "filed_counts": {
        "Cedar Ridge Trust": 3
      }
    },
    {
      "doc_type": "commitment_register",
      "document_id": "CMT-2026-0009",
      "as_of": "2026-07-31",
      "commitments": [
        {
          "commitment_id": "JOB-2026-0001-VEN-1001-01",
          "job_id": "JOB-2026-0001",
          "vendor_id": "VEN-1001",
          "vendor_name": "Ironwood Sandbox Supply Co",
          "contract_type": "subcontract",
          "amount_cents": 2780000,
          "schedule_of_values": [
            {
              "line": 1,
              "description": "Mobilization",
              "amount_cents": 495000
            },
            {
              "line": 2,
              "description": "Rough-in",
              "amount_cents": 1185000
            },
            {
              "line": 3,
              "description": "Final finish",
              "amount_cents": 1100000
            }
          ],
          "change_orders": [
            {
              "change_order_id": "JOB-2026-0001-VEN-1001-01-CO-01",
              "original_commitment_id": "JOB-2026-0001-VEN-1001-01",
              "description": "Added scope per owner directive",
              "amount_cents": 100000
            }
          ]
        },
        {
          "commitment_id": "JOB-2026-0002-VEN-1002-01",
          "job_id": "JOB-2026-0002",
          "vendor_id": "VEN-1002",
          "vendor_name": "Foxglove Mock Freight LLC",
          "contract_type": "subcontract",
          "amount_cents": 640000,
          "schedule_of_values": [
            {
              "line": 1,
              "description": "Haul-off",
              "amount_cents": 480000
            },
            {
              "line": 2,
              "description": "Site restoration",
              "amount_cents": 160000
            }
          ],
          "change_orders": []
        },
        {
          "commitment_id": "JOB-2026-0003-VEN-1003-01",
          "job_id": "JOB-2026-0003",
          "vendor_id": "VEN-1003",
          "vendor_name": "Harborview Demo Services Inc",
          "contract_type": "purchase_order",
          "amount_cents": 925000,
          "schedule_of_values": [
            {
              "line": 1,
              "description": "Materials release",
              "amount_cents": 925000
            }
          ],
          "change_orders": []
        }
      ]
    }
  ]
}